fdn/__init__.py
fdn/__main__.py
fdn/data/__init__.py
fdn/data/config.json
fdn/data/__pycache__/__init__.cpython-310.pyc
fdn/data/corpora/words.zip
fdn/fdnlib/__init__.py
fdn/fdnlib/fdncfg.py
fdn/fdnlib/fdncli.py
fdn/fdnlib/fdnutils.py
fdn/fdnlib/ucrypt.py
fdn/fdnlib/udb.py
fdn/fdnlib/utils.py
fdn-2022.6.26.2937.dist-info/METADATA
fdn-2022.6.26.2937.dist-info/WHEEL
fdn-2022.6.26.2937.dist-info/entry_points.txt
fdn-2022.6.26.2937.dist-info/top_level.txt
fdn-2022.6.26.2937.dist-info/RECORD
