Metadata-Version: 2.1
Name: fdn
Version: 2022.6.26.2937
Summary: uniformly change file or directory names
Home-page: https://github.com/hobbymarks/fdn
Author: hobbymarks
Author-email: ihobbymarks@gmail.com
License: MIT
Platform: UNKNOWN
Classifier: License :: OSI Approved :: MIT License
Classifier: Programming Language :: Python :: 3
Classifier: Programming Language :: Python :: 3.8
Classifier: Programming Language :: Python :: 3.9
Classifier: Programming Language :: Python :: 3.10
Requires-Dist: click (>=8.0.0)
Requires-Dist: setuptools (>=49.6.0)
Requires-Dist: unidecode (>=1.2.0)
Requires-Dist: cryptography (>=3.4.7)
Requires-Dist: colorama (>=0.4.4)
Requires-Dist: pandas (>=1.2.4)
Requires-Dist: wcwidth (>=0.2.5)
